{
  "$schema": "https://developer.microsoft.com/json-schemas/fabric/item/report/definition/visualContainer/2.0.0/schema.json",
  "name": "ex_slicer_risk_tier",
  "position": {
    "x": 845.3333333333334,
    "y": 334.0,
    "z": 1382.0,
    "width": 386.6666666666667,
    "height": 74.0,
    "tabOrder": 1382
  },
  "visual": {
    "visualType": "slicer",
    "query": {
      "queryState": {
        "Values": {
          "projections": [
            {
              "field": {
                "Column": {
                  "Expression": {
                    "SourceRef": {
                      "Entity": "GoldRenewalScores"
                    }
                  },
                  "Property": "risk_tier"
                }
              },
              "queryRef": "GoldRenewalScores.risk_tier",
              "nativeQueryRef": "risk_tier",
              "active": true
            }
          ]
        }
      }
    },
    "objects": {
      "title": [
        {
          "properties": {
            "show": {
              "expr": {
                "Literal": {
                  "Value": "true"
                }
              }
            },
            "fontSize": {
              "expr": {
                "Literal": {
                  "Value": "10D"
                }
              }
            },
            "fontFamily": {
              "expr": {
                "Literal": {
                  "Value": "'Segoe UI'"
                }
              }
            },
            "text": {
              "expr": {
                "Literal": {
                  "Value": "'Risk tier'"
                }
              }
            }
          }
        }
      ],
      "data": [
        {
          "properties": {
            "mode": {
              "expr": {
                "Literal": {
                  "Value": "'Dropdown'"
                }
              }
            }
          }
        }
      ]
    },
    "drillFilterOtherVisuals": true
  }
}